{
  "case_id": "case_047621",
  "source": {
    "source_id": "source_converted",
    "file": "D:\\动画\\众生界\\.case-library\\converted\\大鉴定师-冰火阑珊.txt",
    "novel_name": "大鉴定师-冰火阑珊",
    "genre": "现代都市"
  },
  "scene": {
    "type": "对话场景",
    "chapter_index": 4,
    "position_ratio": 0.003,
    "word_count": 1000
  },
  "quality": {
    "overall_score": 10,
    "emotion_value": 5.8,
    "confidence": 0.26,
    "has_ai_taste": false
  },
  "tags": {
    "techniques": [],
    "keywords": [
      "说道"
    ],
    "recommended_writers": [
      "墨言",
      "剑尘"
    ]
  },
  "content_preview": "第四章全是假货\n\n“小伙子，想要什么，我这里的玉器可都是上好的和田玉，做工精美，各朝代都有啊，看这沁色，极为难得的三色沁啊。”看到陈逸在自己的摊子前停了下来，摊主连忙热情的招呼着，一边拿着玉器向他介绍。\n“我随便看看，你先忙。”陈逸笑着对摊主说道，然后在摊子上的几十件玉器上不断观察着。\n看到了其中一件漂亮的玉器，他不由蹲下身子，拿了起来，这是一个弥勒佛雕像挂件，看起来倒是十分的精致，于是陈逸向其拍上了一张鉴定符。\n他已经基本可以确定，别人是看不到鉴定符的，否则，在当时拍到那两个骗子的画上时，肯定会被那两个紧盯着他的骗子发现。\n“弥勒佛玉器挂件（假），制作年代：距今三十天；玉器用料：人造玻璃经高压烧铸而成。”\n“材料缺陷：与真玉相比，人造玻璃制成之玉，上有明显气泡，而且质量略轻，热稳定性极差，在接触皮肤时，真玉会保持温凉之感，人造玻璃则会产生温热之感……”\n“玉器价值：人造玻璃，化学烧铸，机器加工，毫无任何价值，长久佩戴可危害人体健康。”\n陈逸瞪大了眼睛，这看起来很美丽的玉，竟然是用人造玻璃制成的，而且鉴定出来的信息，也与之前有些不同。\n“呵呵，小伙子果然识货，这可是上等和田玉，经过大师",
  "extract_time": "2026-04-01T10:32:24.410522"
}