{
  "case_id": "case_039807",
  "source": {
    "source_id": "source_converted",
    "file": "D:\\动画\\众生界\\.case-library\\converted\\明末苍茫-人在夜半.txt",
    "novel_name": "明末苍茫-人在夜半",
    "genre": "现代都市"
  },
  "scene": {
    "type": "对话场景",
    "chapter_index": 1,
    "position_ratio": 0.002,
    "word_count": 1000
  },
  "quality": {
    "overall_score": 10,
    "emotion_value": 5.5,
    "confidence": 0.2,
    "has_ai_taste": false
  },
  "tags": {
    "techniques": [],
    "keywords": [],
    "recommended_writers": [
      "墨言",
      "剑尘"
    ]
  },
  "content_preview": "第001章迷茫\n\n天启五年四月十一日辰时，山东登州府威海卫城东北三里水师营盘中，战船福海号在涌浪中微微摇摆，赵烈在船舱中发呆，身后伴当万基屏息而立。\n对于小赵大人的时常发呆万基等一众伴当早已是习以为常，嗯，自从八个月前，百户赵烈同伴当万基、黄汉、张鼓声、余大宝、杜立等人打闹，从福海号船头落水摔晕醒来后，时不时的发呆已是赵烈的一种习惯，一天没有数次的呆滞就不是赵烈赵大人。\n赵烈如果听到万基心里的嘀咕一定会发飙，靠，我从天朝盛世穿到明末乱世，心中之郁闷、惶恐也是你个明朝小白能晓得的，一时想不开言行失当也属正常嘛，易位相处，让你小子穿到天朝只怕被精神病。\n赵烈一月前刚刚过十六周岁，正式成丁，成为大明威海水师福海号船长，这多亏了明朝大好的世袭军户制度，因为老爹赵海明乃是大明登莱水师指挥同知、威海卫水师指挥使，自家一个儿子早立军功荣任百户，多大点事嘛，在大明军户体例里将这等小事办妥就是上官一句话的事。\n赵烈上世三十出头，正在一个香港医药公司人辽省的销售经理，一米七的个头，外貌平常，有过女友，没有婚姻，事业凑合。一天，坐船从大连到青岛途中，在甲板上散步时因突如其来的大风浪失足落水，然后，就没有然后",
  "extract_time": "2026-04-01T10:32:06.657579"
}