{
  "case_id": "case_033206",
  "source": {
    "source_id": "source_converted",
    "file": "D:\\动画\\众生界\\.case-library\\converted\\大宫.txt",
    "novel_name": "大宫",
    "genre": "历史军事"
  },
  "scene": {
    "type": "开篇场景",
    "chapter_index": 6,
    "position_ratio": 0.043,
    "word_count": 1500
  },
  "quality": {
    "overall_score": 10,
    "emotion_value": 8.1,
    "confidence": 0.167,
    "has_ai_taste": false
  },
  "tags": {
    "techniques": [
      "对话描写",
      "情绪强化"
    ],
    "keywords": [
      "第一章"
    ],
    "recommended_writers": [
      "云溪",
      "苍澜"
    ]
  },
  "content_preview": "第4节：第一章 眸倾(4)\n师父也是张大嘴巴，不可置信。\n师父走到奴兮面前，问她：\"你以前读过书？\"\n奴兮点了点头，谦逊地说：\"小时候娘亲曾教过我一些。\"\n\"读过什么书？\"\n奴兮想了想，回答道：\"不过是《诗经》、《古诗十九首》和一些唐诗宋词，不过我最喜欢的李太白的诗几乎可以全都背下来。\"\n我们很惊讶，这个比我还要小几岁的小女孩，懂得的诗竟然比我还多！\n师父挑了挑眉，颇感兴趣：\"那小姐可否背一首李太白的诗给老夫听听？\"\n奴兮爽快地答应了：\"那不如我就给老师背一下李太白的《江上吟》吧。\"\n奴兮调整了一下呼吸，不紧不慢地背出了那首有名的《江上吟》：\"木兰之枻沙棠舟，玉箫金管坐两头。美酒尊中置千斛，载妓随波任去留。仙人有待乘黄鹤，海客无心随白鸥。屈平词赋悬日月，楚王台榭空山丘。兴酣落笔摇五岳，诗成笑傲凌沧洲。功名富贵若长在，汉水亦应西北流。\"\n奴兮背诗真的很好听，抑扬顿挫，仿佛将人带到了诗的意境中去。\n我见平时不苟言笑的师父微眯双眼，捋着他一向引以为豪的白胡须，随着诗的节奏轻轻摇头，一副陶醉的样子，不禁感到有些好笑。\n这天，师父脸上挂着少见的笑容，对我们也和蔼了许多。我偷偷地看着前排专心致志听",
  "extract_time": "2026-04-01T10:31:50.342683"
}