{
  "case_id": "case_045797",
  "source": {
    "source_id": "source_converted",
    "file": "D:\\动画\\众生界\\.case-library\\converted\\做自己想做的人.txt",
    "novel_name": "做自己想做的人",
    "genre": "现代都市"
  },
  "scene": {
    "type": "环境场景",
    "chapter_index": 5,
    "position_ratio": 0.333,
    "word_count": 1000
  },
  "quality": {
    "overall_score": 10,
    "emotion_value": 5.8,
    "confidence": 0.217,
    "has_ai_taste": false
  },
  "tags": {
    "techniques": [
      "对话描写"
    ],
    "keywords": [
      "环境",
      "周围"
    ],
    "recommended_writers": [
      "云溪"
    ]
  },
  "content_preview": "第一章心态魔方 \n一、谁在控制我心态。心态是人情绪和意志的控制塔，是心态决定了行为的方向与质量。我们可以做一个简单的试验：在一个大教室里，如果你周围有熟人、朋友，也有你不认识的人。当要求每一个人与四周的人握手致意时，人们将怎样想怎样做呢？有的热情，有的勉强，有的做得好，有的做得不好；有的就只找认识的人，否则就不愿做……握手应该人人都会吧，既不需要知识、阅历，更与智商技能无关，而仍然质量参差，因人而异，就因为握手的对象不同时，你的心态不同。心态就是内心的想法，是一种思维的习惯状态。荀子说\"心者，形之君也，而神明之主也\"，意即\"心\"是身体的主宰，是精神的领导。心态使人做出超常的行为。战国时卫国有一个叫弥子瑕的人，因为长得俊美而深得卫王宠爱，被任命为侍臣，随驾左右。有一次，弥子瑕因为母亲生病，就私驾卫王的马车回家探视。按当时卫国的法律，私下使用大王车马者，当处以斩断双脚的刑罚。卫王知道此事后，不但没有处罚弥子瑕，反而称赞他：\"子瑕真孝顺啊！为了生母的病，竟然忘了刑律。\"又有一天，弥子瑕陪同卫王游果园，弥子瑕摘下一个桃子，吃了一半，另一半献给卫王。卫王高兴地说：\"子瑕真爱我啊！好吃的桃子不愿独",
  "extract_time": "2026-04-01T10:32:20.201815"
}