{
  "case_id": "case_048204",
  "source": {
    "source_id": "source_converted",
    "file": "D:\\动画\\众生界\\.case-library\\converted\\如何掌控自己的快乐和工作.txt",
    "novel_name": "如何掌控自己的快乐和工作",
    "genre": "现代都市"
  },
  "scene": {
    "type": "环境场景",
    "chapter_index": 3,
    "position_ratio": 0.273,
    "word_count": 1000
  },
  "quality": {
    "overall_score": 10,
    "emotion_value": 5.0,
    "confidence": 0.267,
    "has_ai_taste": false
  },
  "tags": {
    "techniques": [
      "伏笔设置"
    ],
    "keywords": [
      "氛围"
    ],
    "recommended_writers": [
      "云溪"
    ]
  },
  "content_preview": "第二章\n工作快乐的两大要素\nWhat Makes Us Happy At Work\n形式上讲，玛丽亚的新工作看上去拥有一切：一家财力雄厚的大公司，有趣的工作内容，令人羡慕的薪水，井井有条的办公室，专门准备餐点的法国厨师，公司还提供健身、免费的水果和按摩。从玛丽亚办公室的窗口往外看，能看到美得让人屏息的风景。\n玛丽亚40多岁，为人随和，职场经验丰富，是位迷人的女士。但是，到新公司才一个月，她就注意到事情很不对。即使公司实力如此雄厚，它却完全没有人力价值和社会价值。公司里同事间相互猜忌、勾心斗角、造谣中伤、性骚扰、暗地里陷害，员工之间相互没有尊重，气氛压抑，有着山雨欲来风满楼的感觉。\n接下来的第二个月，玛丽亚一直在仔细考虑，怎么才能改变这些现象。到了第三个月，玛丽亚意识到自己对这些事情几乎无能为力，反倒很容易陷入恶性循环。没有找好下一份工作，玛丽亚就辞职离开了。\n目前，玛丽亚在做出版编辑，同时还负责公司的人力资源管理，以及工作氛围的改善。她的薪水比起以前低了很多，但是生活质量大大提高了。她说：“我现在相信工作是可以快乐的，现在已经到了一个快乐工作的时代，并希望帮助传播这一令人高兴的信息。”",
  "extract_time": "2026-04-01T10:32:25.711480"
}