{
  "case_id": "case_007359",
  "source": {
    "source_id": "source_converted",
    "file": "D:\\动画\\众生界\\.case-library\\converted\\行动的召唤：有效提升网络营销力.txt",
    "novel_name": "行动的召唤：有效提升网络营销力",
    "genre": "现代都市"
  },
  "scene": {
    "type": "环境场景",
    "chapter_index": 1,
    "position_ratio": 0.5,
    "word_count": 1000
  },
  "quality": {
    "overall_score": 10,
    "emotion_value": 5.0,
    "confidence": 0.167,
    "has_ai_taste": false
  },
  "tags": {
    "techniques": [
      "伏笔设置"
    ],
    "keywords": [],
    "recommended_writers": [
      "云溪"
    ]
  },
  "content_preview": "第一部分，制作故事板也是开始美学设计的地方。毕竟，在斯坦福大学的劝导技术实验室的研究中，近半数的消费者（46.1%）认为网站的信誉首先基于视觉设计的吸引力程度。\n设计图解模型时，要牢记网站是个互动劝导工具，不是营销部门华而不实的东西。需要设计的三个原因：\n（1）唤起顾客的记忆与图像和您的品牌的联想。\n（2）使您看起来更专业。\n（3）帮助网站说服顾客更有效。\n每个图片、设计都会帮助顾客更加信任您的公司、产品或服务吗？对说服顾客有用吗？\n设计师很讨厌受约束，但是对转换设计的错误观念比比皆是，很多这样的观念都被认为是“最佳实践方法”。一旦设计师知道了真正有效并无约束的转换设计，他们会接受的。这是设计师在图解模型阶段应该遵循的一些基本准则：\n停止不连贯的设计\n很多网站有醒目的页面，它们看起来“很好”或似乎都是“为了品牌”。但是醒目页面与别的页面的观感不同，会使访客失去方向，还会影响处于购买冲动中的顾客的心情。醒目页面是顾客取得有关信息的障碍，常常被误用，要求访客选择路径，而路径的选择由信息建构管理倒比较好。\n许多网站的结算过程的观感与其他网页不同（这与很多托管解决方案同时发生）。但它对去除无关",
  "extract_time": "2026-04-01T10:30:51.869864"
}