{
  "case_id": "case_003180",
  "source": {
    "source_id": "source_converted",
    "file": "D:\\动画\\众生界\\.case-library\\converted\\六月之兽1.txt",
    "novel_name": "六月之兽1",
    "genre": "现代都市"
  },
  "scene": {
    "type": "环境场景",
    "chapter_index": 3,
    "position_ratio": 0.079,
    "word_count": 1000
  },
  "quality": {
    "overall_score": 10,
    "emotion_value": 5.3,
    "confidence": 0.217,
    "has_ai_taste": false
  },
  "tags": {
    "techniques": [
      "伏笔设置",
      "情绪强化"
    ],
    "keywords": [
      "景象"
    ],
    "recommended_writers": [
      "云溪"
    ]
  },
  "content_preview": "第一章 请叫我少爷（2）\n数以万计的高中学生顿时从学校的不同角落涌了出来，宛如一阵黑压压的潮水，瞬间聚集在宛如广场般巨大的操场上。所有人被眼前这惊奇的景象吸引，纷纷伸长了脑袋，张大嘴巴，吃惊地看着蔚蓝色天空中，那个黑点渐渐地降落……降落……\n“他是人还是神仙啊！怎么会从那么高空中降落……”\n“我们快点接住他！千万不能让他有任何危险！”\n“他就是那个传说中的转校生……市长的儿子——藤季乡！”\n然而，“少年”降落的方式却让所有人大吃一惊：快要落地的时候，她忽然将身上的降落伞一把退去，然后一个后空翻，足够帅气地一脚踏在大理石砖面上，闪耀地单膝着地……\n一瞬间，华丽的学院建筑统统沦为了“少年”的背景。\n白皙的肌肤带着圣洁的光芒，清秀的面容不带任何表情，却又散发出极具诱惑的美丽。薄薄的眼镜后面是不屑而与世无争的神情，青涩的瞳孔中仿若有一片清澈的山川在暗自流动，无法猜测它的流向，却能让人感受到那从心底而发的悸动。\n高挑的身材，使深蓝色的制服显得如此英气逼人，更是让“少年”身边的一草一木暗淡失色。\n就像是耀眼的明星坠入大海，即将掀起一番惊涛骇浪。\n那一刻，时间仿佛凝滞了一般，所有人都屏住呼吸。他们瞪",
  "extract_time": "2026-04-01T10:30:43.182516"
}