{
  "case_id": "case_048386",
  "source": {
    "source_id": "source_converted",
    "file": "D:\\动画\\众生界\\.case-library\\converted\\凤舞大清1.txt",
    "novel_name": "凤舞大清1",
    "genre": "现代都市"
  },
  "scene": {
    "type": "环境场景",
    "chapter_index": 7,
    "position_ratio": 0.087,
    "word_count": 1000
  },
  "quality": {
    "overall_score": 10,
    "emotion_value": 5.3,
    "confidence": 0.167,
    "has_ai_taste": false
  },
  "tags": {
    "techniques": [],
    "keywords": [],
    "recommended_writers": [
      "云溪"
    ]
  },
  "content_preview": "第三章 与君初相识，犹如故人归(1)\n接下来的二十多天，可用一个字来形容我堪称古代青少年妇女典范的行为举止：“乖”，用两个字来形容自己的心态：“悲哀”。\n我至今还记得用毛笔写第一幅字时，熠熙老兄几乎抓狂的表情，没办法，在用键盘比用手写还熟练的现代，就算偶尔写字也是我行我素的‘我’字体，现在突然用毛笔写‘柳体’，能画的不象桃符才怪呢，只可惜砸了人家正牌菀葶所创下的才女招牌，从那以后我就像回到了万恶的旧社会（什么‘像’，根本就是），被虐待的跟个陀螺似的转个不停。辰时（7～9时），在‘晚娘脸’表哥的监督下临帖；巳时（9～11时），听先生讲解诗经和四书（大学，中庸，论语，孟子）；午时（11～13时），进午膳外加临帖，倘若吃饭时故意磨蹭，便会被某人咬牙切齿的瞪个没完，唉！未时（13～15时），继续听先生讲解诗经四书；申时（15～17时），跟沈宛舅母练琴；酉时（17～19时），用晚膳外加礼仪训练；戌时（19～21时），跟沈宛舅母绘画和练习剑舞……然后回屋再临帖两张以备翌日检查，等到最后洗漱睡觉时我连东西南北都分不清了，第二天周而复始，没有双休日，更不要指望谁会良心发现给我减负，什么世道啊，干脆再给",
  "extract_time": "2026-04-01T10:32:26.071994"
}