{
  "case_id": "case_005647",
  "source": {
    "source_id": "source_converted",
    "file": "D:\\动画\\众生界\\.case-library\\converted\\我的董事长老婆-黑夜de白羊.txt",
    "novel_name": "我的董事长老婆-黑夜de白羊",
    "genre": "武侠仙侠"
  },
  "scene": {
    "type": "对话场景",
    "chapter_index": 2,
    "position_ratio": 0.25,
    "word_count": 1000
  },
  "quality": {
    "overall_score": 10,
    "emotion_value": 6.1,
    "confidence": 0.26,
    "has_ai_taste": false
  },
  "tags": {
    "techniques": [
      "伏笔设置",
      "情绪强化"
    ],
    "keywords": [
      "问道",
      "说道"
    ],
    "recommended_writers": [
      "墨言",
      "剑尘"
    ]
  },
  "content_preview": "第二回。没有人，能够阻挡我们诸神的力量！等时机一到，我们自然会赐予整个人间诸神黄昏！”\n但就在这时候，一道黑光忽然破开了地面，然后撕破了会议桌，擦着拜勒的鼻子，直接重开了天花板，然后消失在更高的空中。\n“这是什么！”\n诸神全都大吃一惊。\n“什么力量！竟然攻到了神界！”\n“这，不可能！”\n诸神乱成一团，拜勒出奇地没有阻止，反而深深地皱起了眉头。\n这股力量……是来自何方！\n而发出这一道撕破空间，冲入神界的炮轰，秦川身体也摇晃了一下，然后慢慢清醒过来，半跪在地上。\n“卧槽……为什么感觉这么累啊……刚刚发生了什么……”\n这段记忆完全都空白了，秦川根本不知道出了什么状况。\n“我怎么跑到这来了……这是哪里……”\n他掏出手机，看了一眼道行，发现他现在所在的位置，是s市最边缘的地方。\n不知道这里刚才是不是发生了什么战斗……希望没有伤及无辜啊。\n秦川暗中祈祷了一下，然后一纵身，想要化身战斗机飞回去。\n但是他刚跳起三四米高，就重新落了下来，重重地摔在了地面上。\n“卧槽……背好痛……看来这次力量透支的很严重啊……”\n秦川苦笑一声，没有办法，只好给总部打了个电话过去。\n很快，一架直升机轰隆隆地飞过来，慢慢停在",
  "extract_time": "2026-04-01T10:30:48.212647"
}