{
  "case_id": "case_030389",
  "source": {
    "source_id": "source_converted",
    "file": "D:\\动画\\众生界\\.case-library\\converted\\喵喵喵.txt",
    "novel_name": "喵喵喵",
    "genre": "游戏竞技"
  },
  "scene": {
    "type": "情感场景",
    "chapter_index": 2,
    "position_ratio": 0.065,
    "word_count": 1000
  },
  "quality": {
    "overall_score": 10,
    "emotion_value": 6.8,
    "confidence": 0.167,
    "has_ai_taste": false
  },
  "tags": {
    "techniques": [
      "伏笔设置",
      "情绪强化"
    ],
    "keywords": [],
    "recommended_writers": [
      "墨言"
    ]
  },
  "content_preview": "第一章 穿越的猫(1)\n故事从宁静的夏日午后开始，太阳晒得我全身暖洋洋的，身下绿草如茵，如果全身肌肤和骨头不是火辣辣地疼，那么一切都十分正常。\n我是谁？我是只猫，中长毛的三花猫，今年两岁，雌性，主人喜欢叫我花苗苗。\n我为什么在此？\n好像是在十楼的阳台上抓麻雀，不小心掉了下来，那时风呼呼响在我的耳边，就像飞翔一样。主人扑到栏杆边，表情惊恐而绝望。我努力地抬头，最后看了一眼天空，有群鸟儿展翅飞过……很快，浓厚的血腥味充满了我的鼻腔和咽喉，最后大脑一片空白，陷入无边黑暗中，什么都不知道了。\n既然不知道，那就不要想，猫的思维很简单，如同一条直线。\n享受现在的美好阳光，缓和身上的疼痛，好好睡个懒觉才是最重要的事，没想到耳边却传来阵阵急切的呼唤声，“老大！老大！你还好吗？怎么被打回猫身了？”\n这声音真烦人，我抖动几下耳朵，换了个姿势，继续入睡。\n没想到那个聒噪的声音却更加急切，继续在我耳边响起，“老大！老大！你快醒醒！”\n我愤怒地睁开眼，想给这个吵我睡觉的家伙一爪子，没想到我并没有看见人的踪影，面前只有一只乌鸦——白色的乌鸦。\n他睁着乌溜溜的圆眼睛，正歪着脑袋看我，似乎有些欣喜，“老大，我总算找到",
  "extract_time": "2026-04-01T10:31:43.898446"
}