{
  "case_id": "batch2_39764",
  "source": {
    "path": "D:\\动画\\众生界\\.case-library\\converted\\幽灵酒店下.txt",
    "novel_name": "幽灵酒店下",
    "genre": "科幻灵异"
  },
  "scene": {
    "type": "对话场景",
    "chapter_index": 45,
    "word_count": 1200
  },
  "content_preview": "第一部明明大团圆了，但观众看得不过瘾，于是第二部一开始，编剧就挥舞着笔杆子峰回路转了。\n“在他们的抢夺中，她的灵魂从天上掉下来，掉进了血瀑布……”\n石飞侠道有不好的预感：“然后？”\n“没了。”\n石飞侠终于知道，原来比死亡更可怕的字眼是‘没了’。\n想到没了，他不免想到伊斯菲尔，心里又沉甸甸起来。虽然他比阿斯蒙蒂斯好一点，还有个盼头，但是这盼头是多久？他们习惯于几千年几万年的计算日子，但是他不习惯，\n他仍然喜欢用一礼拜一个月来计算。\n“你知道我为什么是淫欲罪么？”阿斯蒙蒂斯看着天空。\n石飞侠道：“不知道。以我的理解，你应该是杀人罪。”\n“因为我爱上的是人类。”\n所以说伊斯菲尔也有淫欲罪？\n石飞侠囧囧地想，然后非常艰难地将伊斯菲尔和淫欲两个字扯在一起。\n好吧，往好里想，伊斯菲尔得的罪越多，离天堂就越远，他们的小日子就过得更安稳……当然，前提是没有阿巴顿半路跑出来玩什么穿越！\n“什么是穿越？”\n一直到阿斯蒙蒂斯提问，石飞侠才发现自己竟然一不小心把心里的念头说出来了。\n“穿越就是……一群人时空旅游的猛人。”\n阿斯蒙蒂斯道：“这是被神所禁止的。”\n“难道真的有人能在时空里来去自如？”石飞侠眼里升起",
  "quality": {
    "score": 10,
    "confidence": 0.85,
    "has_ai_taste": false,
    "ai_expressions": [
      [
        "一股",
        1
      ],
      [
        "让人",
        1
      ]
    ]
  },
  "extract_time": "2026-04-01T09:39:06.990096",
  "batch": "batch2"
}