{
  "case_id": "batch2_89137",
  "source": {
    "path": "D:\\动画\\众生界\\.case-library\\converted\\茅山守尸人-庞家康少.txt",
    "novel_name": "茅山守尸人-庞家康少",
    "genre": "科幻灵异"
  },
  "scene": {
    "type": "对话场景",
    "chapter_index": 781,
    "word_count": 1200
  },
  "content_preview": "第780章地府篇：回阳廿年\n\n庞康的到来，让庞浩又惊又喜，也有些如坐针毡，毕竟这里是阴间，活人不应该下来的。\n到了庞浩的府邸，庞康差点勃然大怒，但无可奈何的是，他不知道找谁泻火。\n“不行，绝对不行，你知道你在干什么？这可是一辈子别想投胎的差事！”庞康当场就拒绝了庞浩。\n“马上跟我回阳间，那里还有很多人在等着你！”\n“为什么？你给我个理由啊！”庞浩问道。\n“你现在才几岁啊？百善孝为先，不孝有三，无后为大，你没听过这句话吗？”庞康问道。\n“还有，你的女朋友是叫王晓萌吧？她哭得死去活来的，难道你忍心？”艾曼丽问道。\n庞浩顿时无语，他没想过庞康都是地仙的人了，居然还想着……\n想到这，庞浩把庞小龙给扯了过来，“这是我儿子，谁说我没后了？”\n但他的心里却在想着王晓萌。\n“我不管，你想当总阴司可以，但你必须把该做的事给我做了，否则我天天到地府闹，看谁能把我怎么样！”庞康开始无理取闹起来了。\n或者更像是跟庞浩撒娇。\n“就不能有别的选择吗？”庞浩无奈的问道。\n“只有一个选择，回阳间二十年，把你应尽的事办完！”庞康想了一会才说道。\n“那么长？那谁来管我这个部门？总阴司又不是虚有其表的！”庞浩问道。\n“你现",
  "quality": {
    "score": 10,
    "confidence": 0.85,
    "has_ai_taste": false,
    "ai_expressions": [
      [
        "仿佛",
        1
      ]
    ]
  },
  "extract_time": "2026-04-01T09:41:18.843172",
  "batch": "batch2"
}