{
  "case_id": "batch2_35467",
  "source": {
    "path": "D:\\动画\\众生界\\.case-library\\converted\\完美星光-五千党.txt",
    "novel_name": "完美星光-五千党",
    "genre": "玄幻奇幻"
  },
  "scene": {
    "type": "开篇场景",
    "chapter_index": 1,
    "word_count": 1500
  },
  "content_preview": "第一章逃港认亲\n\n夕阳无限好，只是近黄昏。\n天色已晚，周遭昏暗一片，景物依稀可见，但山中并无平静，各种鸟兽叽叽喳喳叫唤，山路连通密林，密林深处走出一人来。\n叶天擦擦额头汗珠，坐在路边小歇，浑身穿着大裤衩，扛着干瘪的轮胎，背上挂着塑料袋，奇异打扮，放在二十一世纪，定会被认作为拾荒者，不过放在1980年代特区，小孩都知道他要干啥。\n沿着草泥小路，一步步走到珠江岸边，叶天眺望南岸，恨不得立即飞过去，几里外就是繁华奢靡、一个月可以赚一千多块的大香港。\n当然一个月赚一千块不是叶天目标。\n将事先准备的姜汤喝了大半，又啃了半个窝窝头，恋恋回首，叶天心情无限复杂。\n“这就要走了。”\n珠江作为泳场的盛况:成百上千市民在一泓江水中强身健体，口号喊得分外响亮，其背后的真正意图大家都心照不宣：为了随时可能发生的远行——偷渡边防线，逃亡到香港。\n偷渡方式可谓五花八门，有的农民借口去割草，划着一只小船便偷渡到香港去了，相比之下，生产队干部似乎更心疼偷渡客划走的那条小船。\n……\n莫名其妙到这个时代好一阵子了，叶天依旧不太习惯这里的日常生活，从早到晚除了稀粥就是窝窝头，钞票也少的可怜，从他恢复意识以来，一共用了五块七",
  "quality": {
    "score": 10,
    "confidence": 0.95,
    "has_ai_taste": false,
    "ai_expressions": [
      [
        "一种",
        1
      ],
      [
        "似乎",
        1
      ],
      [
        "好像",
        1
      ]
    ]
  },
  "extract_time": "2026-04-01T09:38:56.774326",
  "batch": "batch2"
}