{
  "case_id": "batch2_08245",
  "source": {
    "path": "D:\\动画\\众生界\\.case-library\\converted\\丹修有点田-盗天书生(1).txt",
    "novel_name": "丹修有点田-盗天书生(1)",
    "genre": "玄幻奇幻"
  },
  "scene": {
    "type": "开篇场景",
    "chapter_index": 1,
    "word_count": 1500
  },
  "content_preview": "第1章 碧玉指环\n越国，明月镇附近的一片旷野荒郊里。\n林凡卖力的用药锄刨开泥土，连根挖起一株一阶初品还灵草，满心欢喜。\n“今天运气不错，挖到两块冰灵矿，一株还灵草，可以卖到七块灵石！”\n轰隆！天地为之一暗！\n无数雷光如金蛇狂舞一般，耀亮了半边天际！\n“啊？方才rì头还老高，怎么突然变天了？好大的雷云！看样子非下一场大暴雨不可，得赶紧回明月镇！”\n林凡赶忙抓起储物袋，拾起药锄，朝着明月镇的方向跑去。\n旷野上，林凡孤零零一人，奔跑的身影格外显著。\n咻！\n天际间划破一道紫红的光华，穿透雷云，赫然落在了林凡身前！\n林凡狠狠吃了一惊，定睛瞧看，只见紫红光华落下，竟然是个宫装女子！\n这宫装女子披着紫红霓裳，散发着淡淡华光，容貌绝美，清丽脱俗，仿佛不染凡尘。但林凡仔细一瞧，见她俏脸煞白，一身的狼狈，伏在地上，看样子十分虚弱。\n若非是她这身狼狈模样，林凡险些儿疑做是仙女下凡！\n“姑娘！你受伤了？我这里有灵药！”\n林凡只是一怔，就赶忙跑到近前，从储物袋中拍出一小瓶初品还灵丹来，递到了紫衣霓裳的宫装女子跟前。\n宫装女子满是深意的打量了一番林凡，又见他递来一阶还灵丹，轻轻推开，苦涩的一笑：“练气一层的小修，",
  "quality": {
    "score": 7.5,
    "confidence": 0.95,
    "has_ai_taste": true,
    "ai_expressions": [
      [
        "一股",
        1
      ],
      [
        "一种",
        1
      ],
      [
        "仿佛",
        4
      ],
      [
        "似乎",
        1
      ],
      [
        "不由得",
        1
      ]
    ]
  },
  "extract_time": "2026-04-01T09:37:55.599564",
  "batch": "batch2"
}