{
  "case_id": "case_029588",
  "source": {
    "source_id": "source_converted",
    "file": "D:\\动画\\众生界\\.case-library\\converted\\释放令(《无辜的血》第二部).txt",
    "novel_name": "释放令(《无辜的血》第二部)",
    "genre": "游戏竞技"
  },
  "scene": {
    "type": "对话场景",
    "chapter_index": 2,
    "position_ratio": 0.667,
    "word_count": 1000
  },
  "quality": {
    "overall_score": 10,
    "emotion_value": 6.0,
    "confidence": 0.2,
    "has_ai_taste": false
  },
  "tags": {
    "techniques": [
      "对话描写"
    ],
    "keywords": [],
    "recommended_writers": [
      "墨言",
      "剑尘"
    ]
  },
  "content_preview": "第一卷。收银台旁的女孩给他找零时几乎没有看他一眼。\n\n释放令（1）\n然后他走到沙夫茨伯里大道，乘十四路汽车到皮卡迪利广场。他给了乘务员一张一英镑的纸币，因为他知道他会需要很多的小额零钱。在皮卡迪利，他将自己关在一个电话亭里。他的口袋日记本的地址页上，用铅笔写着所有姓帕尔弗里的人的姓名首字母和电话号码。他很感激这个女孩有如此非同一般的名字。这些姓帕尔弗里的人中没有以\"小姐\"称呼的，但这并没有让他感到惊讶。他曾在什么地方看到过，如果在广告上说你是个女人，那就是在邀请奇怪的电话。当他列出了八个电话号码后，就在书店的袋子上用铅笔写了\"P.帕尔弗里小姐\"几个字。没有谁看见过这个包，但是他很小心地用很大的不规则的笔画组成这几个字，使它们尽量与自己的笔迹不同。然后，在拿起电话筒前，他在脑海里又复述了一遍他要说的话： \n\"对不起，打搅您了，我是耶兰。我在圣詹姆斯公园的长凳上发现了一本书。书是在福伊尔书店买的，书袋上写着\"P.帕尔弗里小姐\"。我想这本书值得我打电话试着找到书的主人。\" \n接听第一个电话的是一个声音沙哑的男人。男人断然地告诉他这 \n①佩夫斯纳（AntoinePevsner，1886-196",
  "extract_time": "2026-04-01T10:31:42.008946"
}