{
  "case_id": "case_030192",
  "source": {
    "source_id": "source_converted",
    "file": "D:\\动画\\众生界\\.case-library\\converted\\执掌娱乐圈-一江寒月.txt",
    "novel_name": "执掌娱乐圈-一江寒月",
    "genre": "青春校园"
  },
  "scene": {
    "type": "情感场景",
    "chapter_index": 3,
    "position_ratio": 0.015,
    "word_count": 1000
  },
  "quality": {
    "overall_score": 10,
    "emotion_value": 6.8,
    "confidence": 0.167,
    "has_ai_taste": false
  },
  "tags": {
    "techniques": [
      "伏笔设置",
      "情绪强化"
    ],
    "keywords": [],
    "recommended_writers": [
      "墨言"
    ]
  },
  "content_preview": "第三章死了都要爱\n\n柳潇潇的男朋友叫方杰，方杰的爸爸是云海市公安局副局长，所以他平rì里在学校嚣张跋扈，谁都不放在眼里。\n今天，万万没想到竟然有人敢在云海跟他叫板。\n方杰以一种匪夷所思的神情怒视着任飞，在他看来，像任飞这种没什么背景的家伙，绝对不敢跟他这么说话。\n任飞知道，既然决定要打造柳潇潇，那方杰这一关是不可避免的，跟这种人即便再好声好气的解释也无济于事，倒不如直接摊牌。\n是你女朋友又怎样？是你女朋友，老子还不能跟她说话了？\n安静的图书馆瞬时变得杀气腾腾，王子皓三人见状，立刻起身赶了过去，站在任飞的身后，相处三年时间，四人早就成了共患难的好兄弟。\n方杰怒视着任飞，威胁道：“任飞，你胆子不小啊，竟然敢打我马子的主意，你应该知道得罪我有什么后果！”\n“方杰，你够了！我们老同学说句话怎么了？”柳潇潇柳眉微皱，显然不喜欢刚才方杰对自己的用词。\n这时，王子皓也上前道：“切，真会给自己长脸，连嘴都没亲过，房间都没开过，还好意思说她是你女朋友，不知道的还以为你是人家的小跟班呢！”\n王子皓此言一出，身边不少知晓两人事迹的学生纷纷窃笑起来。\n方杰尴尬万分，右手食指怒指王子皓：“王子皓，你是不是想找麻",
  "extract_time": "2026-04-01T10:31:43.447518"
}