{
  "case_id": "case_033758",
  "source": {
    "source_id": "source_converted",
    "file": "D:\\动画\\众生界\\.case-library\\converted\\电影梦幻系统-右眼有泪.txt",
    "novel_name": "电影梦幻系统-右眼有泪",
    "genre": "青春校园"
  },
  "scene": {
    "type": "情感场景",
    "chapter_index": 1,
    "position_ratio": 0.003,
    "word_count": 1000
  },
  "quality": {
    "overall_score": 10,
    "emotion_value": 7.1,
    "confidence": 0.167,
    "has_ai_taste": false
  },
  "tags": {
    "techniques": [
      "情绪强化"
    ],
    "keywords": [],
    "recommended_writers": [
      "墨言"
    ]
  },
  "content_preview": "第一章我叫叶开！\n\n“各位，当你们看到这段视频的时候，就证明我已经离开了！不要为我伤心，死亡并不是终结，而是另一个开始……我将会在天国为各位祝福……另外，小……叶倩，原来我一直不敢正视自己的内心，但是现在，我想对你说，我爱你！当初的我因为过不去心里的坎，所以才会拒绝你，哪怕我们并没有血缘关系！现在，我的生命即将走到尽头，我终于可以正视你的感情，虽然这看上去有点晚……再见了！各位！”\n叶开看着自己手里的手机上播放的视频，嘴角露出一丝苦笑了。\n想不到，自己竟然还会有机会再来一次！\n叶开，华明国h市的一名普通市民，和大多数普通人一眼，叶开过着庸庸碌碌的生活，每天没事就和朋友一起喝酒，一起吹牛，然后在家里玩游戏，安安分分的做着一个宅男应该做的事，但是这一切却在某一天骤然终结！\n叶开看着安静的躺在病床上的那个绝美的女子，整颗心都在刹那间碎成了一片片！\n为什么？！为什么？！\n叶开跪在雨中声嘶力竭的质问着苍天，为什么要让自己心爱的女子离自己而去！而且还是因为什么狗屁的癌症？！\n叶开并不相信医院的诊断，因为她的身体一直很好，从小到大自己都是被她欺负过来的，根本不可能患有癌症！\n叶开决定自己调查真相，经",
  "extract_time": "2026-04-01T10:31:51.733347"
}