{
  "case_id": "batch2_11397",
  "source": {
    "path": "D:\\动画\\众生界\\.case-library\\converted\\仙朝-蛇吞鲸.txt",
    "novel_name": "仙朝-蛇吞鲸",
    "genre": "武侠仙侠"
  },
  "scene": {
    "type": "环境场景",
    "chapter_index": 5,
    "word_count": 1000
  },
  "content_preview": "第5章记忆X神通\n\n天庭在阳间设立阴神的主要目的就是为了监察天下，将阳间的风吹草动报上地府或是天庭，而土地则是最低级的一种。\n土地，便相当于一个在人间的小吏，每一个土地分管一部分的地界，每隔一月将自己所管辖的土地上面发生的事情事无巨细的报给城隍，由城隍报地府，当然，如果发生了紧急的事件，也不会局限于一月一次。\n这也是为什么人死之后，地府会对任何一个人的一生都有一个极为详细的记载一般，因为有这些阴神的存在，你的一举一动根本就不可能逃的过监察，所谓举头三尺有神明，便是这个道理。\n为了能让阴神在阳间长久的生存，天庭打造了十数万的法宝神印，也就是像做官的一般的法宝，一是用来证明阴神的身份，二则是让阴神有一个栖身之地，对于阳间的十数万阴神而言，神印才是他们的根本，其次才是神像，但是后来，在人间的阴神们发现，通过大量的香火愿力可以提升自己的实力和神通，比起在阴间修炼来，利用阳间的香火愿力修炼更快，于是乎，争斗便在阴神之间展开了。\n越是在人烟鼎盛的地方，这种香火之力的争夺就越厉害，阴神所占的地盘越大，信奉他们的人越多，他的实力也就越强。\n而为了争夺这些香火之力，除了阴神之间互相争斗之外，阴神们还要争",
  "quality": {
    "score": 10,
    "confidence": 0.5900000000000001,
    "has_ai_taste": false,
    "ai_expressions": [
      [
        "一种",
        1
      ]
    ]
  },
  "extract_time": "2026-04-01T09:38:01.276622",
  "batch": "batch2"
}