{
  "case_id": "batch2_99654",
  "source": {
    "path": "D:\\动画\\众生界\\.case-library\\converted\\道修至尊-博雅兰台.txt",
    "novel_name": "道修至尊-博雅兰台",
    "genre": "武侠仙侠"
  },
  "scene": {
    "type": "环境场景",
    "chapter_index": 1037,
    "word_count": 1000
  },
  "content_preview": "第1024章融合？重生？（大结局！）\n\n至尊魔皇自爆所引发的毁灭，是灾难性的，漫天的黑色魔气带着强劲的能量，横扫整个崇云山，乃至崇云山下另外几座不算低矮的山峰，已然是被至尊魔皇的自爆给波及，乃至是直接夷为了平地。\n一群妖鬼魔三族联军的精锐修真者，和云清派门派联盟的一群大乘期渡劫期修真者，却也算是处于了爆炸的中心点，受到的波及，自然是无与伦比的！\n只是瞬间的事情，整个天空直接就被黑色魔气包裹了起来，抬头看去，看不到任何一丁点的光明！黑色魔气弥漫的天空黯然，也让崇云山下无数山峰被粉碎的一干二净！\n妖鬼魔三族联军修真者，来了一百多个，此时被至尊魔皇自爆所波及，先前又死掉数十人，此时剩下的三族联军精锐高手，不过区区十来人。\n而这十来个人，却是在抬头盯着天空看了一番之后，想也没想，直接相互搀扶着转身就跑了个无影无踪！\n而修真者这边，经历至尊魔皇这一阵自爆，却也死伤惨重，剩下的几十个大乘期渡劫期修真者，看着自己满身狼狈，乌烟瘴气的周围摇头叹息。\n天空上的情况怎么样了呢？这是这些仅存下来的一群大乘期渡劫期修真者心里共同的想法，苏文鼎死了吗？至尊魔皇死了吗？那三大金仙死了吗？\n连对面的妖鬼魔三族一群黑",
  "quality": {
    "score": 10,
    "confidence": 0.6339999999999999,
    "has_ai_taste": false,
    "ai_expressions": []
  },
  "extract_time": "2026-04-01T09:41:57.248038",
  "batch": "batch2"
}