{
  "case_id": "batch2_11008",
  "source": {
    "path": "D:\\动画\\众生界\\.case-library\\converted\\他从末世来-竹茶.txt",
    "novel_name": "他从末世来-竹茶",
    "genre": "科幻灵异"
  },
  "scene": {
    "type": "转折场景",
    "chapter_index": 1278,
    "word_count": 1000
  },
  "content_preview": "第一部电影的男主角是云落，女主角是纳兰涩琪。在电影上映之后，可以说是爆红了世界各国，这让云落的明星之路更上一层楼。已然是红透半边天。\n对于纳兰涩琪，云落还是很有诚意的，其实安初遇也知道自家老公啥德行，别的不说，有缘分的妹子特别的多，都是搞不懂云落没事就宅在家里，为什么会招惹这么多出色的姑娘。安初遇不得不承认的是，不管是各个方面。她都是很落后的。\n唯一让安初遇获得了最后胜利的法宝，那就是安初遇很早就是云落的女朋友了。两个人的情侣关系一直都是很好很好的，没有分手过，一直在一起，然后就是结婚成家。\n这一切的一切都让安初遇很是感恩生活的，虽然在身边还是会出现别的姑娘。安初遇还是有些肚量的，也是云落整个人都是发生了极大的变化。不仅仅是出名，还是变得又高又帅的，让安初遇都觉得我去这么帅的美男子竟然是我老公。\n其实有不少云落的粉丝，都是认为安初遇配不上云落的，拿得出手的除了青梅竹马初恋女朋友之外。似乎也没有别的了。但就是这样，安初遇快了一步，比颜沉鱼快了一步，就真的是一步一个脚印的，最后赢得了云落正妻的宝座。\n这种事情，说起来也是缘分啊，要不是如此，安初遇也不能成为第一个怀上云落小宝宝的姑娘。跟云落",
  "quality": {
    "score": 10,
    "confidence": 0.88,
    "has_ai_taste": false,
    "ai_expressions": [
      [
        "仿佛",
        1
      ],
      [
        "似乎",
        1
      ]
    ]
  },
  "extract_time": "2026-04-01T09:38:00.389795",
  "batch": "batch2"
}