{
  "case_id": "batch2_00516",
  "source": {
    "path": "D:\\动画\\众生界\\.case-library\\converted\\87时机：抓住时机的人，错过时机的人.txt",
    "novel_name": "87时机：抓住时机的人，错过时机的人",
    "genre": "游戏竞技"
  },
  "scene": {
    "type": "结尾场景",
    "chapter_index": 55,
    "word_count": 800
  },
  "content_preview": "断结论：“现在正是单干独立的时机。”\n在每个人的人生中，健康管理、应试学习、就业活动、存款等，没有人会为我们决定这些事情开始的时机。“开始行动”的时机，就是我们的“自我责任”。“该需要这个了。最好是该开始了”或者是“现在开始这个还为时尚早”。当你产生这样或那样的感觉的时候，这就意味着一个“开始行动”的时机到来了。首先，最重要的是迈出最初的一步，着手做最重要的事情。当你呈现出“现在开始这个还为时尚早”这样的一种思想状况时，表示你精神上认为时间还有余裕，但是等到真的开始着手的时候，才发现有点事关紧迫，迫不得已，时间所剩无几。这样一般不会取得好结果的。\n在工作中，往往是上司和顾客决定任务和事情的最终期限（或者产品的交货期），但是他们不决定“开始时机的期限”。要是别人给你限定好“开始的时机”的话，你一定会觉得非常被动，非常为难。\n有些人明明知道开始行动是十分重要的，但就是迟迟不能开始去做。对于这些人来说，最重要的一点就是他们应该好好考虑一下自己总是推迟行动的原因究竟是什么，诸如“做得不完美，就不想干”“嫌踏踏实实地干事情太麻烦”“认为自己有困难”等，这些情绪也许都是抓不住开始时机的因素。减肥、",
  "quality": {
    "score": 10,
    "confidence": 0.7,
    "has_ai_taste": false,
    "ai_expressions": [
      [
        "一种",
        2
      ]
    ]
  },
  "extract_time": "2026-04-01T09:37:41.403275",
  "batch": "batch2"
}