{
  "case_id": "batch2_98436",
  "source": {
    "path": "D:\\动画\\众生界\\.case-library\\converted\\追逐日光.txt",
    "novel_name": "追逐日光",
    "genre": "现代都市"
  },
  "scene": {
    "type": "人物出场",
    "chapter_index": 5,
    "word_count": 1000
  },
  "content_preview": "第二章坠入无尽深渊(1)\n我欲永生，一切皆如我意。 \n——史蒂文?莱特（Steven Wright） 如是说 \n我是谁？ \n在我过去的一生，我慢慢成长为美国毕马威会计师事务所的首席执行官和董事长，这是美国四大会计师事务所之一，有着百年的辉煌，拥有40亿美元的资产和20 000名员工。我在这里度过了一天又一天的美妙生活，通常我的每一天是这样度过的：开几个客户见面会，这是我最喜欢做的事情；我至少会和自己核心领导团队中的一个成员见面；我会和纽约以及其他城市的合伙人通电话进行沟通，看看我能帮他们做些什么；我还要解决一些突发情况；有时我还要和公司的竞争对手进行讨论，商讨如何共同达成商业目标；我完成了电子日历上列出的种种事项。三年前，我被公司的合伙人推举为公司的首席执行官，当时我就致力于实现三个目标：第一，拓展业务（这并没有什么好奇怪的，因为任何一个公司只有扩大业务才能继续生存下去）；第二，要提高服务质量并降低风险；第三，对我最重要也是对公司长期发展有利的一点，那就是让我们的公司成为更好的工作场所，让员工更乐意为之效劳，能让员工协调好工作和生活。我一直就认为，要致力于为员工服务，让他们觉得工作和生",
  "quality": {
    "score": 10,
    "confidence": 0.5,
    "has_ai_taste": false,
    "ai_expressions": [
      [
        "似乎",
        1
      ]
    ]
  },
  "extract_time": "2026-04-01T09:41:52.419633",
  "batch": "batch2"
}