{
  "case_id": "batch2_14829",
  "source": {
    "path": "D:\\动画\\众生界\\.case-library\\converted\\傲世皇庭-帝绝心.txt",
    "novel_name": "傲世皇庭-帝绝心",
    "genre": "玄幻奇幻"
  },
  "scene": {
    "type": "战斗场景",
    "chapter_index": 3,
    "word_count": 1000
  },
  "content_preview": "的《淬体诀》可以相提并论的。\n《筑脉诀》和《淬体诀》虽然都是基础修炼功法，但也存在明显的等级差别，即使只是一品的差距，也足以改变一个人的武道之路。上品《筑脉诀》可以让一个武者修炼到窥武境巅峰，如果再有什么机缘之类的，修炼到武者境也不是不可能。\n而中品的《淬体诀》即使你天赋再高，修炼到极致，也顶多大多窥武境八重，从这里也足以看出其中的差距有多大。而且修炼上品《筑脉诀》能够让武者的气血能量更加的凝实，战斗更加占优势。\n“上品《筑脉诀》，族里不是只有一部中品的《淬体诀》嘛？难道少爷说的是真的，这不是族里的功法。”秦山心里暗暗道，虽然他是个仆人，但也是少族长的仆人，这些东西还是知道的。\n于是秦山连忙点头道“多谢少爷，多谢少爷，秦山一定不会对其他人说的，打死都不会。”这点古岩到还是相信，秦山跟了他十多年，什么品性他都一清二楚。\n于是古岩便开始以口述的方式将这部上品的《筑脉诀》传给了秦山，所幸的是秦山曾跟古岩一起学过字，不然古岩倒还真是要伤些脑筋了。\n记完那篇功法后，秦山眼睛红红的盯着古岩，眼里留着一颗颗滚烫的泪珠。他这不是因为这功法的缘故，而是被古岩对他的信任而感动的。毕竟他一个仆人，古岩却还这",
  "quality": {
    "score": 10,
    "confidence": 0.63,
    "has_ai_taste": false,
    "ai_expressions": [
      [
        "可想而知",
        1
      ]
    ]
  },
  "extract_time": "2026-04-01T09:38:07.661703",
  "batch": "batch2"
}