{
  "case_id": "case_034278",
  "source": {
    "source_id": "source_converted",
    "file": "D:\\动画\\众生界\\.case-library\\converted\\造化之门-鹅是老五.txt",
    "novel_name": "造化之门-鹅是老五",
    "genre": "玄幻奇幻"
  },
  "scene": {
    "type": "环境场景",
    "chapter_index": 3,
    "position_ratio": 0.002,
    "word_count": 1000
  },
  "quality": {
    "overall_score": 10,
    "emotion_value": 5.0,
    "confidence": 0.167,
    "has_ai_taste": false
  },
  "tags": {
    "techniques": [],
    "keywords": [
      "环境"
    ],
    "recommended_writers": [
      "云溪"
    ]
  },
  "content_preview": "第二章前途难卜\n\n“水已经弄好了，我帮你去洗澡吧。”等宁城将一些事情整理到差不多的时候，纪洛妃已经再次走了出来说道。\n宁城虽然和田慕琬恋爱了两三年时间，可是最多也只是限于拉一下手而已。除此之外，他就没有做过其余更进一步的动作。现在纪洛妃要帮他洗澡，宁城一下就感觉到不自然起来。他肯定之前的宁城也没有让纪洛妃洗过澡，不是因为和他的想法一样，而是因为纪洛妃的长相。\n“我自己来就行了……”宁城连忙说道。\n觉察到了纪洛妃疑惑的目光，宁城赶紧从榻上爬了起来，勉强的扶着床沿说道，“你看，我现在已经可以自己走动了。”\n虽然在牢狱中被折磨了一段时间，但是回来喝了一点水后，宁城已经勉强可以行动。\n看见宁城真的可以摇摇晃晃的走进去洗澡，纪洛妃愈发疑惑起来。在她的印象中，宁城是绝对不会拒绝别人伺候他的。对宁城来说，只有伺候的不好一顿打，而绝对不会说自己来就行这种话。难道是宁城知道家破人亡，所以比之前明白了许多事理？\n不过这些疑惑很快就被纪洛妃放在了一边，也不再去管宁城自己洗澡的事情，自顾去煮了一些米粥。宁城修炼了这么多年都无法聚气，这固然是因为他不愿意吃苦修炼，同样和他的资质极差也有关系。现在宁家家破人亡，宁",
  "extract_time": "2026-04-01T10:31:53.037167"
}