{
  "case_id": "case_038918",
  "source": {
    "source_id": "source_converted",
    "file": "D:\\动画\\众生界\\.case-library\\converted\\八荒武神-张牧之.txt",
    "novel_name": "八荒武神-张牧之",
    "genre": "玄幻奇幻"
  },
  "scene": {
    "type": "环境场景",
    "chapter_index": 4,
    "position_ratio": 0.003,
    "word_count": 1000
  },
  "quality": {
    "overall_score": 10,
    "emotion_value": 5.0,
    "confidence": 0.217,
    "has_ai_taste": false
  },
  "tags": {
    "techniques": [
      "情绪强化"
    ],
    "keywords": [
      "环境"
    ],
    "recommended_writers": [
      "云溪"
    ]
  },
  "content_preview": "第九百八十三章三师齐聚\n龙宫能够克制神族，但具体是怎么克制的，罗成还不知道，只能按照青龙说的照做。\n当完成青龙所说的方法后，罗成等着看龙宫要如何消灭神族，他本以为在体内的龙宫会出现，最后将神族降服。\n片刻后，罗成没有见到龙宫的影子，正当他以为是不是方法不对的时候，对面三个神族露出十分惊恐的样子，但不是看着他，而是他的背后。\n罗成好奇的看向身后，顿时被震惊在原地，不知道在什么时候，有一个高达百丈的魁梧巨人站在他后面。\n这不是真人，但又不是虚影，仿佛真实存在，但又能发现他是透明的。\n惊讶后，罗成感受到无上的威严从这个人身上散发出来，于是认真打量起来。\n这个巨人裸着上半身，宛如钢水浇灌而成，线条分明，让人感到狂野，五官也是一张坚毅的脸庞，双眼炯炯有神，仿佛能够洞察世间一切黑暗。\n“王？！”\n对面那三个神族见到这个巨人，被吓得半死，内心中的恐惧被唤醒。\n“王？”罗成想到那个传说中的人类，也是倍感惊讶。\n“神族，死！”\n巨人说出生涩难懂的语言，罗成不懂这门语言，但却明白这是什么意思，连他自己都不知道怎么回事。\n旋即，巨人大手一伸，横空而去，抓向那三个神族。\n几乎是没怎么反抗，或者说没办法反抗，三",
  "extract_time": "2026-04-01T10:32:04.323844"
}