{
  "case_id": "case_023025",
  "source": {
    "source_id": "source_converted",
    "file": "D:\\动画\\众生界\\.case-library\\converted\\素颜繁花梦.txt",
    "novel_name": "素颜繁花梦",
    "genre": "历史军事"
  },
  "scene": {
    "type": "环境场景",
    "chapter_index": 6,
    "position_ratio": 0.088,
    "word_count": 1000
  },
  "quality": {
    "overall_score": 10,
    "emotion_value": 5.3,
    "confidence": 0.167,
    "has_ai_taste": false
  },
  "tags": {
    "techniques": [
      "伏笔设置",
      "情绪强化"
    ],
    "keywords": [
      "周围"
    ],
    "recommended_writers": [
      "云溪"
    ]
  },
  "content_preview": "第4节：他的微笑如水荡漾，目光里却闪烁着小恶毒(3)\n果然，不多会，原本晴朗无云的天空，忽然刮起了大风，并且从天际尽头飘过来大块大块的乌云，隐约已有雷声响了起来。眼看一场大雨即将降临。我暗暗发笑，这群土包子，一定会拿我当下凡的神仙一般尊崇了。\n（2）\n李三脸色顿时变得惊慌，周围的人也鼓噪起来：“这丫头尽然能未卜先知，果然要下雨了……”\n我拾起衣裙，抢先躲在台阶之上，我刚一立定，雨就哗啦哗啦下起来了。\n看着手忙脚乱收拾着鸟笼子的李三，我含笑说：“我可以取走我的鸟了吗？”\n那李三却鼓着一脸横肉，横蛮不讲理地说：“我只是说，赢了归你，但是却没有说不收银子啊。看在你预测准了下雨的份上，我就一两银子把它便宜卖给你算了。”\n我一愣，顿时气不打一处来。本小姐虽然自小被逼学习琴棋书画，可真正的爱好却只有一样，那就是与人打赌，而且逢赌必赢。所以我最恨打赌不算话没有赌品的人。一两银子我不是没有，我也不在乎这点钱，可是我就是恼恨他食言。什么人嘛，这不是欺负本小姐年轻吗？真是的，终于明白为什么野蛮女友当道了，都是让这些渣滓们给闹腾不得不野蛮一些的。\n我大喝一声：“李三你个毛线，愿赌服输，你做人怎么可以这么无耻",
  "extract_time": "2026-04-01T10:31:26.745307"
}