{
  "case_id": "batch2_83570",
  "source": {
    "path": "D:\\动画\\众生界\\.case-library\\converted\\绝脉武神-临渊.txt",
    "novel_name": "绝脉武神-临渊",
    "genre": "玄幻奇幻"
  },
  "scene": {
    "type": "心理场景",
    "chapter_index": 1082,
    "word_count": 1000
  },
  "content_preview": "第1115章大结局\n\n“死吗，死有何惧？我死了，你也随即会死，但我死前见到了儿子，然后跟心爱的妻子死在一起，这样的死，叫做死得其所，你才会死无葬身之地！”杨天煞怒吼道。\n无天武帝终于面色变了，他以灵魂替代并且控制灵魂的逆天手段，便是要给杨天煞一个重创。\n可是杨天煞的话表明，他已经在最后关头，无视了无天武帝施展在易辰身上的任何手段。\n不管易辰怎么变，易辰始终是易辰，是他杨天煞的儿子。\n人族武者，自从修炼以来，每一次突破，都是灵魂和肉身的蜕变。\n从这个意义上来说，每一个人都在不断的变化中。\n无天武帝在变，杨天煞也在变。\n易辰的这种变化，同样可以看做是另一种修为和境界的提升呢？\n唯一能够不变的，有且只有一个，那便是武者之本心。\n杨天煞本心认同易辰，把易辰当儿子，易辰虽然灵魂被神秘道符控制，但他的本心依然认同杨天煞这个父亲……就够了！\n刹那间，杨天煞神念通达，身上气息急剧攀升，竟然直接越过了混沌武神的层次，直达玄之又玄、虚无缥缈的主宰境。\n无天武帝第一次从杨天煞身上，感受到“我不如他”的强大气息。\n但这时候，无赦神剑依然极速临近。\n剑光闪烁着森寒的银芒。\n无天武帝又笑了，杨天煞强大又如何，既然",
  "quality": {
    "score": 10,
    "confidence": 0.88,
    "has_ai_taste": false,
    "ai_expressions": [
      [
        "一种",
        1
      ],
      [
        "忍不住",
        1
      ]
    ]
  },
  "extract_time": "2026-04-01T09:40:59.806793",
  "batch": "batch2"
}