{
  "case_id": "batch2_14445",
  "source": {
    "path": "D:\\动画\\众生界\\.case-library\\converted\\偷香邪医-挥墨客.txt",
    "novel_name": "偷香邪医-挥墨客",
    "genre": "青春校园"
  },
  "scene": {
    "type": "情感场景",
    "chapter_index": 1571,
    "word_count": 1000
  },
  "content_preview": "第一千五百七十章偷香邪医不容易（大结局）\n\n鸿蒙神祖打断神葬邪祖的话，嘴角浮起一丝淡淡的微笑。\n这时，神葬邪祖清楚感觉到，他的身体正在从内部燃烧着，燃烧的源头是那些没爆发出来的可怕力量。这些力量在鸿蒙神祖封印之力的催动下开始暴走，暴走的结局，就是同归于尽。\n林逸的神色顿时一变，正欲出手阻止，却被鸿蒙神祖抓住了手。\n“傻小子，来不及了，就让我作为鸿蒙神祖，最后为鸿蒙宇宙做点事，好吗？”鸿蒙神祖微笑着说道，神色平静无比。\n林逸咬了咬牙，道：“可你这么做，想过天命吗？她现在在我的神魂之境出不来，等她能出来时，她能接受这一切吗？”\n鸿蒙神祖闻言苦笑，摇了摇头，道：“在她心中，我只是一个不称职的丈夫和父亲，她早就不需要我了，又怎会因为我的离开而悲伤呢？林逸小子，神葬邪祖消失之后，神葬宇宙也拜托你了，光靠鸿钧那小子，我可不放心……”\n“闭嘴！鸿蒙老儿，你以为你真的能杀我？你在做梦，在做梦！”神葬邪祖大吼大叫，林逸的脸色顿时一变，他感觉到整个神葬宇宙都在颤抖，似乎到了崩溃的边缘。\n神葬邪祖的反应越来越疯狂，他一把抓住鸿蒙神祖的身体，用力将其往外拔，像拔萝卜似的。\n鸿蒙神祖的脸色无比痛苦，他没想到神葬",
  "quality": {
    "score": 10,
    "confidence": 0.92,
    "has_ai_taste": false,
    "ai_expressions": [
      [
        "仿佛",
        1
      ],
      [
        "似乎",
        1
      ],
      [
        "让人",
        1
      ]
    ]
  },
  "extract_time": "2026-04-01T09:38:06.810648",
  "batch": "batch2"
}