{
  "case_id": "case_047183",
  "source": {
    "source_id": "source_converted",
    "file": "D:\\动画\\众生界\\.case-library\\converted\\零之使魔第6卷赎罪的赤炎石.txt",
    "novel_name": "零之使魔第6卷赎罪的赤炎石",
    "genre": "历史军事"
  },
  "scene": {
    "type": "对话场景",
    "chapter_index": 2,
    "position_ratio": 0.25,
    "word_count": 1000
  },
  "quality": {
    "overall_score": 10,
    "emotion_value": 5.5,
    "confidence": 0.2,
    "has_ai_taste": false
  },
  "tags": {
    "techniques": [
      "伏笔设置",
      "情绪强化"
    ],
    "keywords": [],
    "recommended_writers": [
      "墨言",
      "剑尘"
    ]
  },
  "content_preview": "第一章\n归乡\n“旅行真是让人心动不已呢！”\n雪丝塔这么叫着，把才人的手臂压在自己的胸口上。\n“与其说心动，倒不如说软绵绵呢……”\n现在是在马车之中，才人和雪丝塔并肩坐在小小的座位上。\n雪丝塔身上穿着草色的连衣裙，脚上穿着绑带长靴，头上还戴着小小的草帽，是一种轻松的外出打扮。黑发而且面容清秀的雪丝塔一旦作出这种打扮，是在显得非常可爱。甚至超越了可爱的极限，转而让人觉得可恨了。你、你这家伙为什么要这么可爱！才人心想。而且难以饶恕的是，这样可爱的雪丝塔明明散发出一种清秀动人的气息，但在行动上却显得相当大胆。跟她并肩坐在一起，她就抱着才人的手臂，猛第压到自己的胸口上。\n雪雪雪、雪丝塔，你要是那那那、那样拉我的手的话、手、手臂就会、就会碰到胸部了，碰、碰上了、软、软绵绵的……当才人以几乎要喜极而泣的声音这么说的时候——\n“啊，我是故意的。”\n雪丝塔却露出爽朗的笑容，若无其事地说出这样的话。\n“怎、怎么……怎么能故意……那个……在旁边有人的地方，你呀……”\n无法把“快住手”这句话说出口的才人，为了安抚自己的良心，作出了形式上的抗议。\n“车夫的话是不用担心的，那只是人偶而已啦。”\n坐在驾车者座位上的",
  "extract_time": "2026-04-01T10:32:23.264481"
}