{
  "case_id": "case_037707",
  "source": {
    "source_id": "source_converted",
    "file": "D:\\动画\\众生界\\.case-library\\converted\\汉明大黄袍-寒虾.txt",
    "novel_name": "汉明大黄袍-寒虾",
    "genre": "历史军事"
  },
  "scene": {
    "type": "对话场景",
    "chapter_index": 3,
    "position_ratio": 0.006,
    "word_count": 1000
  },
  "quality": {
    "overall_score": 10,
    "emotion_value": 5.8,
    "confidence": 0.2,
    "has_ai_taste": false
  },
  "tags": {
    "techniques": [
      "伏笔设置",
      "情绪强化"
    ],
    "keywords": [
      "笑道"
    ],
    "recommended_writers": [
      "墨言",
      "剑尘"
    ]
  },
  "content_preview": "第三章最强演说家\n\n杨帆从客栈走出来。已经很久没有睡得这么舒爽了。当初穿越过来，正好被隐居在农村的祖大寿救了。以前出租房再不济，好歹床还是有的。到了祖大寿家，杨帆只有睡地铺的份了，条件可想而知。\n手里的豆浆油条，刚刚捞出来，冒着热气。杨帆往摊子里一坐，将油条沾了沾香稠的豆浆，塞进嘴里嚼着。\n“小兄弟，你这吃法倒是新颖。这油条讲究酥脆，你这一沾，可就没了那口感了。”\n杨帆笑道：“你可知这油条的来历？”\n一旁人来了兴致，纷纷竖耳倾听。杨帆吃了一口油条，道：“这油条，又叫油炸桧。相传南宋年间，奸相秦桧害死忠臣岳飞。百姓很不啖其肉，吞其骨，便用面粉搓成长条状，用棍子一压，当成秦桧和其妻王氏，下油锅翻炸。临安百姓正愁难舒心头之怒，便吃‘油炸桧’来表达对奸相秦桧的恨意，这油条才流传至今。”\n杨帆边讲边用手将油条分成两半，笑道：“至于我这么吃，觉得光下油锅还不足以泄恨，还得浸一浸猪笼。”\n点心摊子上的百姓大多家底有些殷实，不然在这饥荒年代，哪吃得起点心。“小哥，这岳飞将军我们这些平头百姓也有耳闻，既然你知道这么多，给讲讲如何？”\n杨帆道：“你们真想听？”\n“想啊！”这免费的说书，谁不想听。点心摊子上",
  "extract_time": "2026-04-01T10:32:01.388731"
}