{
  "case_id": "batch2_72836",
  "source": {
    "path": "D:\\动画\\众生界\\.case-library\\converted\\玄门高手在都市-五志.txt",
    "novel_name": "玄门高手在都市-五志",
    "genre": "现代都市"
  },
  "scene": {
    "type": "对话场景",
    "chapter_index": 1348,
    "word_count": 1200
  },
  "content_preview": "第1314章我要和我的朋友们在一起\n\n徐福双手在胸前结出了一个法印，黑色的尸气如同洪水一般，从他的身体中狂涌而出，瞬间就将白玉京的整片天地，都给笼罩在其中，浸染成了墨黑色。强大的压迫力凭空出现，重重的压在李思辰等人身上，不仅压的他们喘不过气，更压的他们全身骨骼‘咔咔’作响。几个实力较弱的人双脚一软，被压的跪倒在了地上。\n“好强！”马小玲面色惨白，拼命的强撑着没有跪下，但全身骨骼传来的剧痛，让她无比的难受。\n“完了，这下子，我们全都得交代在这里了。”弘法和尚心有不甘的说。\n刚才那雷霆的一击，耗光了所有人体内的灵力。原本以为就算不能够灭掉徐福，也能够给与其重创，为己方争取到获胜的机会。可谁也没有料到，徐福竟然强到了这种可怕的地步，在那让天地都为之变色的一招面前，仅仅只是受了点小伤，而且还能够马上发动更为恐怖的反击！\n望着如乌云一般压下来的滚滚尸气，所有人的心中，都升腾起了一丝绝望。\n只有李思辰还没有放弃。\n因为他还有一个杀招！一个早早就开始布局的杀招！\n李思辰飞快的伸手入兜，掏出了一只小瓷瓶，用力的扔向了徐福。\n在金刚杵上驭风咒的催动下，这只小瓷瓶就像是子弹一般，速度快的让人看不清。\n“黔",
  "quality": {
    "score": 10,
    "confidence": 0.85,
    "has_ai_taste": false,
    "ai_expressions": [
      [
        "一股",
        2
      ],
      [
        "让人",
        1
      ]
    ]
  },
  "extract_time": "2026-04-01T09:40:33.162358",
  "batch": "batch2"
}