{
  "case_id": "batch2_54859",
  "source": {
    "path": "D:\\动画\\众生界\\.case-library\\converted\\星语者：蓬莱的烟火·双子座颦.txt",
    "novel_name": "星语者：蓬莱的烟火·双子座颦",
    "genre": "现代都市"
  },
  "scene": {
    "type": "结尾场景",
    "chapter_index": 82,
    "word_count": 800
  },
  "content_preview": "遇到了你。\n坦白说，刚开始，我并没有认真，只当是一场游戏。我的生命是永恒的，但是我的记忆只能维持一年。一年的时光只够用来玩一场游戏。\n但是，不知道什么时候起，你已经成为我所有的记忆。\n即使是在一年内，我也因为法术修炼的失误，而很容易忘记东西。但是，对于你，我却从未忘记。你的声音，你的样子，我全部都记得好清楚，好清楚。\n当我发现，三天外的记忆里只有你的时候。我在想，或者，这就是所谓的爱吧。我很希望这是爱，因为我渴望我能够去爱。但是我时间太短了，我来不及弄清楚这到底是不是爱，只好跟着自己的感觉走了。\n如果可以选择，我愿意拿一切来换，永生也好，灵魂也罢，只要我可以将这段记忆永远得保存下来，只要我可以继续这样爱你。即使是你将来要抛弃我，要让我坠入撕心裂肺的境地，我也不会后悔，决不后悔。\n在有限的生命里，真挚地爱到生命的最后一刻，这哪里是永生所可以比拟的快乐？\n但是，对不起，我做不到，不是不愿，是不能。\n记得吗？你给我讲解“无可奈何”这个成语的时候，我无论如何都不明白，把你气得半死。现在我懂了。\n但是，我现在打算用最后一个办法。我不知道是否会成功。但是我会努力去试。如果，我成功了，我们就去餐厅庆",
  "quality": {
    "score": 10,
    "confidence": 0.7,
    "has_ai_taste": false,
    "ai_expressions": []
  },
  "extract_time": "2026-04-01T09:39:47.725957",
  "batch": "batch2"
}