{
  "case_id": "case_015819",
  "source": {
    "source_id": "source_converted",
    "file": "D:\\动画\\众生界\\.case-library\\converted\\大明星系统-射手座李不二.txt",
    "novel_name": "大明星系统-射手座李不二",
    "genre": "青春校园"
  },
  "scene": {
    "type": "对话场景",
    "chapter_index": 2,
    "position_ratio": 0.001,
    "word_count": 1000
  },
  "quality": {
    "overall_score": 10,
    "emotion_value": 5.5,
    "confidence": 0.26,
    "has_ai_taste": false
  },
  "tags": {
    "techniques": [
      "情绪强化"
    ],
    "keywords": [
      "问道"
    ],
    "recommended_writers": [
      "墨言",
      "剑尘"
    ]
  },
  "content_preview": "第2章艺考型专家\n\n众人惊疑不定间，顾小凡朝着燕影的方向一鞠手，郎声道:\n“我小顾虽不是什么大家大院的孩子，不过亏得祖辈萌阴，家父在燕京电影制片厂从业13年，又在中央戏剧学院干了11年，可以说我本人就是在中戏八大金刚，燕影四大导师熏陶下长大的孩子～～\n不吹牛的讲，这些老师教授都在澡堂里被我小顾帮忙搓过背，所以你们的考官**穿什么牌子的内裤我都一清二楚～～”\n看周围的人一片哄笑，虽然情绪被调动起来了，却还都是半信半疑的样子，顾小凡也不气馁。\n毕竟这年头ps个照片忽悠人的事情太多了，也不是那么容易令人信服，继续着他的“表演”。\n他看似随便指着下面一名学生家长问道：\n“您孩子参加了前几天的中戏一试没有，在中戏的考号是多少？”\n“考……考了～学号……学号是……你等等～”那个学生家长愣了一下，然后从包里掏出了一张皱巴巴的准考证念道：\n“5005657～”\n“5657号……”顾小凡微做思索状后，用高深莫测的语气道：\n“恩……算起来您孩子应该是一试第三天下午考的……那您孩子的主考老师是王志闻吧～？\n王志闻最热**话剧，特别钟**《雷雨》的桥段，但是最厌恶街舞，一看到跳街舞的考生就头疼～”\n顾小凡刚才",
  "extract_time": "2026-04-01T10:31:10.333341"
}