{
  "case_id": "case_009059",
  "source": {
    "source_id": "source_converted",
    "file": "D:\\动画\\众生界\\.case-library\\converted\\入侵型月-我是唐僧我不骑白马.txt",
    "novel_name": "入侵型月-我是唐僧我不骑白马",
    "genre": "青春校园"
  },
  "scene": {
    "type": "对话场景",
    "chapter_index": 4,
    "position_ratio": 0.024,
    "word_count": 1000
  },
  "quality": {
    "overall_score": 10,
    "emotion_value": 5.5,
    "confidence": 0.2,
    "has_ai_taste": false
  },
  "tags": {
    "techniques": [
      "伏笔设置",
      "情绪强化"
    ],
    "keywords": [],
    "recommended_writers": [
      "墨言",
      "剑尘"
    ]
  },
  "content_preview": "第四章初战\n\n从穗群原学园出发，沿着纵横交错的街道，穿过犹如迷宫一般的都市建筑群，就能看到一座面积广阔，绿茵重重的山丘。\n阳光照射在茂密的树木上，只有一小部分才被允许穿过树丛，洒向地面，两者在地面上构成了斑斑驳驳宛如碎花地毯似地美丽精致。\n在这充斥着生命与温暖气息的丛林深处，一条石板铺就的阶梯状石阶静静的横穿整个山林，尽头就是当地有名的柳洞寺。\n好不容易告别了藤村大河，柳洞零观带着放学的愉快心情，穿过树林，沿着阶梯回到家里。\n推开古朴的木门，他看到身为主持的父亲端坐在正对山门的走廊上，手中拿着一杯清茶，似乎是在等人的样子。\n“零观，你过来。”\n看到柳洞零观回来，他立即招手将其唤乐过去，然后指了指身边的蒲团，示意他坐下来。\n柳洞零观奇怪的咂了咂嘴，听话的坐了下来。\n“父亲，有什么事情吗？”\n闻言，他将杯子放在一边的地板上，严肃的看着大儿子：“零观，一会儿和我一起出去，我刚刚接到一份除魔委托。”\n“什么？”\n柳洞零观惊讶了。\n在他的记忆里，父亲从来不会带他参与除魔的工作，这次是怎么了？父亲怎么会决定把我带上呢？\n对于即将参与除魔的事实，柳洞零观虽然觉得奇怪，但却并没有感觉害怕，心中还反而有",
  "extract_time": "2026-04-01T10:30:55.463079"
}