{
  "case_id": "case_026400",
  "source": {
    "source_id": "source_converted",
    "file": "D:\\动画\\众生界\\.case-library\\converted\\风满楼.txt",
    "novel_name": "风满楼",
    "genre": "青春校园"
  },
  "scene": {
    "type": "对话场景",
    "chapter_index": 1,
    "position_ratio": 0.1,
    "word_count": 1000
  },
  "quality": {
    "overall_score": 10,
    "emotion_value": 6.0,
    "confidence": 0.2,
    "has_ai_taste": false
  },
  "tags": {
    "techniques": [
      "对话描写",
      "情绪强化"
    ],
    "keywords": [],
    "recommended_writers": [
      "墨言",
      "剑尘"
    ]
  },
  "content_preview": "第1章 \n还没有真正到夏天，海水温度大抵还徘徊在摄氏十七八度左右，水上联欢会已经开始了。\n游艇雪白的一只只并列在本市最山明水秀的菠萝湾，年青男女挥手与邻船的友人打招呼，他们模仿欧洲人出海的打扮，泳衣外边套一件大毛衣或毛巾衫，苗条的两条腿已经晒成金棕色，这样的活力这样的青春，看上去的确令人心旷神怡。\n恒昌号长五十公尺，第一次落水，簇新的甲板上坐着几个少女，正在调笑。\n有人说：\"听说宦晖与宦楣就要回来工作。\"\n另一个嗤一声笑出来，\"那真是一对活宝贝。\"\n\"是你的令表兄同令表妹哪。\"\n\"嘿，宦楣要带一个洋人回来，她妈不准，还在讲条件，讲不拢不一定回得来。\"\n\"去年不是已经带过一个红头绿眼的回来住了一个暑假？\"\n\"那个已经拆开，\"有人抢着说，\"她一向喜欢外国人。\"\n\"你最关心宦家的事了，哈哈哈，那是你未来小姑，做嫂子的有没有想过要约束约束她？\"\n那少女忽然拉下了脸，咬牙切齿的说：\"谁同宦家有什么关系！从来没有见过那么好色的一家人，父、子、女，一个印子印出来，荒淫无道。\"\n大家见她形容得那么严重，忍不住大笑起来，清脆的笑声传得老远，在蓝天白云绿水中淡出。\n先头那少女脱下外套，跃入水中。\n\"她赌气",
  "extract_time": "2026-04-01T10:31:34.845188"
}