{
  "case_id": "batch2_108436",
  "source": {
    "path": "D:\\动画\\众生界\\.case-library\\converted\\零之使魔第6卷赎罪的赤炎石.txt",
    "novel_name": "零之使魔第6卷赎罪的赤炎石",
    "genre": "玄幻奇幻"
  },
  "scene": {
    "type": "悬念场景",
    "chapter_index": 9,
    "word_count": 1000
  },
  "content_preview": "第八章 火炎之赎罪\n早上刚过四点。\n太阳还没升起、天空依然一片漆黑。\n魔法学院的上空，出现了一艘小型侦察舰。\n敏努维尔站在甲板上，直直地看着天空。\n瓦尔德小心翼翼地不发出一点脚步声，慢慢接近敏努维尔背后。身为风系四方级魔法师的他，只要有心隐藏自己的气息，就可以变得跟空气差不多。\n瓦尔德想试一下敏努维尔。\n他真的是能把这么困难的作战引向成功的人吗？瓦尔德对此产生了疑问。\n然而，看来瓦尔德是杞人忧天了。\n在能感觉到气息的好几倍的距离之外，敏努维尔向瓦尔德开口道：\n“你这样试我又有什么意义呢，子爵？”\n瓦尔德吓了一跳。\n敏努维尔连头也没有回。\n而且就算他回头看，周围也是一片漆黑，什么也看不见，应该不会看见自己的影子才对。\n明明是这样……不知道他用了什么方法，竟然能从那么远的地方察觉到瓦尔德的接近。只能说他的确是个经验丰富的老手了。\n“想不到真的能够顺利来到这里呢。”\n敏努维尔仍然没有回头低声说。\n瓦尔德一边感叹，一边走近敏努维尔。\n“我们运气比较好。不过，进攻的人一般都不会想到自己也会受到进攻的啦。”\n虽然一路上避过了不少魔法师的使魔或者侦察舰组成的警哨线……不过能够不被任何人发现飞到这里，",
  "quality": {
    "score": 10,
    "confidence": 0.88,
    "has_ai_taste": false,
    "ai_expressions": [
      [
        "似乎",
        1
      ]
    ]
  },
  "extract_time": "2026-04-01T09:42:27.822050",
  "batch": "batch2"
}