{
  "case_id": "case_005793",
  "source": {
    "source_id": "source_converted",
    "file": "D:\\动画\\众生界\\.case-library\\converted\\重生逍遥道-黑弦.txt",
    "novel_name": "重生逍遥道-黑弦",
    "genre": "玄幻奇幻"
  },
  "scene": {
    "type": "对话场景",
    "chapter_index": 2,
    "position_ratio": 0.002,
    "word_count": 1000
  },
  "quality": {
    "overall_score": 10,
    "emotion_value": 5.5,
    "confidence": 0.2,
    "has_ai_taste": false
  },
  "tags": {
    "techniques": [
      "情绪强化"
    ],
    "keywords": [
      "说道"
    ],
    "recommended_writers": [
      "墨言",
      "剑尘"
    ]
  },
  "content_preview": "第2章醒来\n\n发现有人闯进院子，白玉一惊，快步走到屋外，白易则摸索着跟了出去。\n院子里闯进了十多人，为首的正是寒峰，寒峰身旁还跟着几个看热闹的富家子弟，在这些阔少爷的身后，是七八个健壮的恶仆，个个横眉立目。\n寒家是永安镇上的大户世家，家产丰厚，财大气粗，在永安镇无人敢惹，这整个布衣巷都是寒家的土地，居住在布衣巷里的穷苦百姓，每年都需要交纳租金。\n穷人在永安镇是置办不起家业的。\n白玉给寒家做过短工，当然认得眼前的恶少，一见是寒峰，女孩儿顿时小脸儿一沉，冷声道：“租子都是年底结，这才年中，还有半年的时间，你来收什么租？”\n“年底结账？”\n寒峰贪婪地盯着少女玲珑有致的身子，邪笑着说道：“我家的地，我想什么时候收租，就什么时候收，今年是年中，明年也许是年初，不但收租，今年的年租还要涨，从一百大钱，改成每年十两银子！”\n涨了百倍的租金，预示着寒峰的恶意，白家兄妹也看出了对方来者不善。\n“你这是漫天要价！”白玉捏紧了小手，怒气冲冲地喊道，脸睱因为气愤而变得通红。\n“布衣巷是我寒家的地产，收多少租子，跟你们这些穷人没有半点关系，住得起就住，住不起的话，就趁早给我搬出永安镇。”\n寒峰狞笑着继续说道：“",
  "extract_time": "2026-04-01T10:30:48.498806"
}