{
  "case_id": "case_020560",
  "source": {
    "source_id": "source_converted",
    "file": "D:\\动画\\众生界\\.case-library\\converted\\重生农村好媳妇-湖涂.txt",
    "novel_name": "重生农村好媳妇-湖涂",
    "genre": "玄幻奇幻"
  },
  "scene": {
    "type": "对话场景",
    "chapter_index": 5,
    "position_ratio": 0.054,
    "word_count": 1000
  },
  "quality": {
    "overall_score": 10,
    "emotion_value": 5.5,
    "confidence": 0.2,
    "has_ai_taste": false
  },
  "tags": {
    "techniques": [],
    "keywords": [
      "笑道"
    ],
    "recommended_writers": [
      "墨言",
      "剑尘"
    ]
  },
  "content_preview": "第5章\n\n话都说到这份上了，宋母不是浑人，知道自己要是露出半点犹豫，那事情就黄了，赶紧打包票道：“大妹子你放心，这要是到了我们家，肯定跟亲闺女一样的。”\n李大红点头，“那行，等建国回来了，就把这事情办了吧。至于过聘礼的事情，你们看啥时候方便就过来，我这都在家里呢。”\n看着事情成了，宋母高兴的不得了，笑道：“那行，我赶紧回去张罗去。”她有看了一眼屋里，高高兴兴的往家里去了。\n宋母一走，张宁就出来了，看着脸上倒是没有啥子不害羞的。\n李大红笑道：“都是一个村的，他们家人还行。你就先在我家好好等着，到时候见了建国，再办事。”\n张宁点点头，心里已经开始对未来生活有期待了。\n也不知道，宋建国会不会喜欢她。想着这个，张宁心里才有了点不好意思。她对宋建国很熟悉，却没有相处过，只是当初被张斌得罪的人绑架之后，是宋建国带着警察来救她的。\n北方某军区\n二营营长姜汉，正拿着信件乐呵呵的跑了过来。\n他身材高大，面容比黑黝黝的兵蛋子要显得白一些，此刻一脸的笑意，再加上他平时训练中的狠劲儿，很让人想到笑面虎这个称号。\n“建国，有你的信，快看看，是不是你媳妇写过来的。”姜汉笑呵呵的将信件递给了宋建国。他是知道宋建国结",
  "extract_time": "2026-04-01T10:31:21.024722"
}