{
  "case_id": "case_028754",
  "source": {
    "source_id": "source_converted",
    "file": "D:\\动画\\众生界\\.case-library\\converted\\傲世丹神-寂小贼.txt",
    "novel_name": "傲世丹神-寂小贼",
    "genre": "玄幻奇幻"
  },
  "scene": {
    "type": "对话场景",
    "chapter_index": 4,
    "position_ratio": 0.002,
    "word_count": 1000
  },
  "quality": {
    "overall_score": 10,
    "emotion_value": 6.1,
    "confidence": 0.32,
    "has_ai_taste": false
  },
  "tags": {
    "techniques": [],
    "keywords": [
      "问道",
      "说道"
    ],
    "recommended_writers": [
      "墨言",
      "剑尘"
    ]
  },
  "content_preview": "第995章脱狱计划\n沈翔知道段崇对一些失去的历史很了解.他急忙问道：“段老.你对这天雷炼狱有多少了解.”\n“了解不多.这里是天雷魔族的掌控之地.天雷魔主算是当年十大魔主中最强的是.所以他邀请其他九个魔主來这里埋伏十天大帝.最后另外九个魔主死去.只有天雷魔主能活下來.他是击伤了十天大帝.但他也好不了哪里去……”段崇说出他知道的.这和之前黄锦天说的那些差不多.\n段崇所知道的.和段崇一样.听完之后.云小刀他们拍手称快.因为当年那帮助天雷魔主的古老势力们.最后竟然被天雷魔主拿來当挡箭牌.\n“这么说.这些魔主是有预谋屠天的.他们不是建立了屠天联盟吗.最后还真的被他们成功了.”沈翔叹气道.不仅仅把天帝杀死.还让十重天分解.\n段崇摇头道：“这我就不清楚了.帝天可不是那么容易灭掉的.而且十天大帝重伤之后.不代表他就任由宰割.他还有力量给自己建造帝墓.然后还做了许多事情……至于帝天是怎么分解.是被谁分解的.那段时间还发生什么大事.这就是我们段家一直所寻找的答案.”\n沈翔看着四周的山岳.原本是一片苍翠.但现在却变成一片枯死.这里的灵气沒有之前那么浓郁了.这并不是因为这里变成炼狱而这样子的.给他的感觉是.这",
  "extract_time": "2026-04-01T10:31:40.200895"
}