{
  "case_id": "batch2_80554",
  "source": {
    "path": "D:\\动画\\众生界\\.case-library\\converted\\第一皇妃·终结篇.txt",
    "novel_name": "第一皇妃·终结篇",
    "genre": "历史军事"
  },
  "scene": {
    "type": "结尾场景",
    "chapter_index": 63,
    "word_count": 800
  },
  "content_preview": "离开了。\n布玛则尽职地待在外殿，继续守候。\n内殿的阿尔玛知道计划已经成功了，松了一口气，躺在床上，舒展了一下筋骨，然后又像是想到了什么，继续傻笑。\n母后……原来是这么娇小的。\n他傻笑着转过身，鼻尖嗅到了枕头上残留的香气。\n他一把把枕头抱在怀里。\n是母后的味道……\n好香啊……\n好舒服……\n离开寝殿的拉拉，马不停蹄地和侍女一起将箱子抬上早已准备好的马车里。车夫是她家里的，所以不需要搪塞什么理由，只说箱子里是祭祀要用的东西，要带到神殿去给辛克斯，就没什么问题了。\n同样的理由，用来对付宫门的守卫也是同样的好用。\n趁着月夜，马车一路驶向神殿，等到了拉曼神殿的后门，拉拉打发了车夫，和侍女将箱子搬进神殿一隅。\n她打开箱子，把隔板拿走。因为颠簸，阿尔缇妮斯有些难受，但可以忍住。\n“好了，到了这里，我就不能送你了，不过你放心，这些人都是父亲的心腹，绝对可靠，她们会送你去卡拉神庙的。”\n阿尔缇妮斯点点头，千言万语只有一句：“谢谢你，拉拉小姐。”\n拉拉觉得有些不好意思，“不要谢了，我这么做，也是为了……为了……”\n“我明白。”\n“好了，你快走吧。”拉拉扶着她从箱子里出来，再将她扶上守候在一旁的另一辆马车。\n",
  "quality": {
    "score": 10,
    "confidence": 0.7,
    "has_ai_taste": false,
    "ai_expressions": []
  },
  "extract_time": "2026-04-01T09:40:52.989509",
  "batch": "batch2"
}