{
  "case_id": "batch2_17323",
  "source": {
    "path": "D:\\动画\\众生界\\.case-library\\converted\\兰陵缭乱3.txt",
    "novel_name": "兰陵缭乱3",
    "genre": "女频言情"
  },
  "scene": {
    "type": "人物出场",
    "chapter_index": 4,
    "word_count": 910
  },
  "content_preview": "第2节：第一章 入狱(2)\n\"三哥是怎么了……这么着急？\"长恭不解地望着他离去的背影。\n恒伽没有说话，眼底飘过一丝复杂的神情，总觉得哪里有点不对劲。\n一直到了傍晚时分，孝琬还没有回，一家人开始焦急起来。\n就在长公主打算派人去找他的时候，刘岷忽然惊慌失措地冲了进来，扑通一声跪倒在地，语无伦次地道：\"不，不好了，王爷，王爷他被皇上押入大牢了！\"\n砰！长公主手中的杯子掉落在地，摔成了碎片。崔澜的脸色也是大变，一旁的小正礼偏偏不合时宜地哇的一声大哭起来，高府里顿时乱作一团……\n\"皇上好端端地怎么会把三哥押入大牢呢？这到底是怎么回事，你一五一十说清楚！\"长恭一把将刘岷从地上扯了起来，焦急地询问道。\n\"是，是这样的。今天小的见到偏邸外有些可疑的人，所以前来禀告了王爷，王爷就打算去看看，谁知道……\"他的眼眶一红，\"谁知道一到偏邸，就发现那里已经被禁卫军包围了。领头的祖大人一见王爷，就立刻令人将王爷抓了起来，说是……说是……王爷有谋反之意……\"\n\"胡说八道，我三哥怎么可能谋反？！无凭无据又怎么能说我三哥有反意！\"长恭在听到\"谋反\"这两个字时被震得心胆俱裂……这是必死之罪啊！一种极度不安和惊慌的黑暗气息",
  "quality": {
    "score": 10,
    "confidence": 0.5,
    "has_ai_taste": false,
    "ai_expressions": [
      [
        "一种",
        1
      ],
      [
        "仿佛",
        1
      ],
      [
        "令人",
        1
      ]
    ]
  },
  "extract_time": "2026-04-01T09:38:12.342954",
  "batch": "batch2"
}